jboss.py
jboss-0.1.3.dist-info/DESCRIPTION.rst
jboss-0.1.3.dist-info/METADATA
jboss-0.1.3.dist-info/metadata.json
jboss-0.1.3.dist-info/RECORD
jboss-0.1.3.dist-info/top_level.txt
jboss-0.1.3.dist-info/WHEEL
